LLoghelper/__init__.py
LLoghelper/log_helper.py
tests/__init__.py
tests/test_log_helper.py
LLoghelper-0.2.0.dist-info/LICENSE
LLoghelper-0.2.0.dist-info/METADATA
LLoghelper-0.2.0.dist-info/WHEEL
LLoghelper-0.2.0.dist-info/top_level.txt
LLoghelper-0.2.0.dist-info/RECORD
