Metadata-Version: 2.1
Name: LLoghelper
Version: 0.2.0
Summary: A helper module for logging.
Home-page: https://github.com/atgczcl/LLoghelper
Author: atgczcl
Author-email: atgzcl@163.com
Classifier: Programming Language :: Python :: 3
Classifier: License :: OSI Approved :: MIT License
Classifier: Operating System :: OS Independent
Requires-Python: >=3.6
License-File: LICENSE
Requires-Dist: colorlog>=6.8.2
